myboxkit/__init__.py
myboxkit/__main__.py
myboxkit/setu.py
myboxkit-0.1.1.dist-info/entry_points.txt
myboxkit-0.1.1.dist-info/METADATA
myboxkit-0.1.1.dist-info/WHEEL
myboxkit-0.1.1.dist-info/RECORD
