Metadata-Version: 2.1
Name: myboxkit
Version: 0.1.1
Summary: 
Author: XiangQinxi
Author-email: xiangqinxi@outlook.com
Requires-Python: >=3.10,<4.0
Classifier: Programming Language :: Python :: 3
Classifier: Programming Language :: Python :: 3.10
Classifier: Programming Language :: Python :: 3.11
Classifier: Programming Language :: Python :: 3.12
Requires-Dist: click (>=8.1.7,<9.0.0)
Requires-Dist: easydict (>=1.11,<2.0)
Requires-Dist: requests (>=2,<3)
